twitter_blocklist/__init__.py
twitter_blocklist/console.py
twitter_blocklist/utils.py
twitter_blocklist-0.6.0.dist-info/entry_points.txt
twitter_blocklist-0.6.0.dist-info/LICENSE
twitter_blocklist-0.6.0.dist-info/WHEEL
twitter_blocklist-0.6.0.dist-info/METADATA
twitter_blocklist-0.6.0.dist-info/RECORD
