Metadata-Version: 2.1
Name: twitter-blocklist
Version: 0.6.0
Summary: Export and import Twitter blocklists
Home-page: https://github.com/zonca/twitter_blocklist
License: MIT
Author: Andrea Zonca
Author-email: code@andreazonca.com
Requires-Python: >=3.6,<4.0
Classifier: License :: OSI Approved :: MIT License
Classifier: Programming Language :: Python :: 3
Classifier: Programming Language :: Python :: 3.6
Classifier: Programming Language :: Python :: 3.7
Classifier: Programming Language :: Python :: 3.8
Provides-Extra: test
Requires-Dist: click (>=7.1.2,<8.0.0)
Requires-Dist: importlib-metadata (>=1.0,<2.0); python_version < "3.8"
Requires-Dist: nbval (>=0.9.6,<0.10.0); extra == "test"
Requires-Dist: progressbar2 (>=3.51.3,<4.0.0)
Requires-Dist: pytest (>=5.4.3,<6.0.0); extra == "test"
Requires-Dist: python-twitter (>=3.5,<4.0)
Requires-Dist: toml (>=0.10.1,<0.11.0)
Project-URL: Repository, https://github.com/zonca/twitter_blocklist
